[{"id":"be53d024.25187","type":"subflow","name":"Calcola HA Start Time","info":"","category":"","in":[{"x":120,"y":160,"wires":[{"id":"f8b38c00.ca732"}]}],"out":[{"x":460,"y":280,"wires":[{"id":"4735def2.79982","port":0}]}],"env":[],"color":"#DDAA99"},{"id":"f8b38c00.ca732","type":"ha-get-entities","z":"be53d024.25187","server":"33257e95.f185a2","name":"sensor.time_online","rules":[{"property":"entity_id","logic":"is","value":"sensor.time_online","valueType":"str"}],"output_type":"array","output_empty_results":false,"output_location_type":"msg","output_location":"payload","output_results_count":1,"x":290,"y":160,"wires":[["c7662a2f.e8b1d8"]]},{"id":"c7662a2f.e8b1d8","type":"change","z":"be53d024.25187","name":"sensor.time_online","rules":[{"t":"set","p":"payload","pt":"msg","to":"$toMillis(payload[0].state)","tot":"jsonata"}],"action":"","property":"","from":"","to":"","reg":false,"x":310,"y":220,"wires":[["4735def2.79982"]],"outputLabels":["msg.minuti_riscaldamento"]},{"id":"4735def2.79982","type":"function","z":"be53d024.25187","name":"","func":"var boot = msg.payload\nvar now = Date.now()\nvar total = now - boot \nvar totalminutes = total / 60000\nmsg.adesso = now\nmsg.boot = boot\nmsg.total = total\nmsg.minutes = totalminutes\nvar minutesround = Math.floor(totalminutes)\nmsg.payload = minutesround\nreturn msg;","outputs":1,"noerr":0,"initialize":"","finalize":"","x":300,"y":280,"wires":[[]]},{"id":"b4682f5f.c5851","type":"comment","z":"be53d024.25187","name":"output MSG.PAYLOAD con il numero di minuti ","info":"","x":290,"y":100,"wires":[]},{"id":"33257e95.f185a2","type":"server","name":"Home Assistant","legacy":false,"rejectUnauthorizedCerts":true,"ha_boolean":"y|yes|true|on|home|open","connectionDelay":true}]